{
  "_note": "Datos canónicos de los 361 puntos estándar OMS (WHO 2008). Para cada punto se incluyen siempre: código, chino, pinyin, traducción al español. La localización detallada y las indicaciones clínicas están completas para los puntos más usados (~60); el resto se irá completando — el archivo está abierto para PRs.",
  "points": {
    "LU1": { "code": "LU1", "meridian": "LU", "chinese": "中府", "pinyin": "Zhōng Fǔ", "spanish": "Palacio Central", "category": ["mu del Pulmón", "punto cruce SP"], "location": "1 cun por debajo de LU2, en el pliegue infraclavicular, lateral a la línea media unos 6 cun.", "indications": ["tos", "asma", "opresión torácica", "dolor de hombro"] },
    "LU2": { "code": "LU2", "meridian": "LU", "chinese": "雲門", "pinyin": "Yún Mén", "spanish": "Puerta de las Nubes", "location": "—", "indications": [] },
    "LU3": { "code": "LU3", "meridian": "LU", "chinese": "天府", "pinyin": "Tiān Fǔ", "spanish": "Palacio Celestial", "location": "—", "indications": [] },
    "LU4": { "code": "LU4", "meridian": "LU", "chinese": "俠白", "pinyin": "Xiá Bái", "spanish": "Acompañante Blanco", "location": "—", "indications": [] },
    "LU5": { "code": "LU5", "meridian": "LU", "chinese": "尺澤", "pinyin": "Chǐ Zé", "spanish": "Pantano del Codo", "category": ["he-mar"], "location": "En el pliegue del codo, lateral al tendón del bíceps braquial.", "indications": ["tos productiva", "asma", "dolor de codo", "fiebre"] },
    "LU6": { "code": "LU6", "meridian": "LU", "chinese": "孔最", "pinyin": "Kǒng Zuì", "spanish": "Apertura Máxima", "location": "—", "indications": [] },
    "LU7": { "code": "LU7", "meridian": "LU", "chinese": "列缺", "pinyin": "Liè Quē", "spanish": "Hendidura Discontinua", "category": ["luo", "comando del CV", "uno de los 4 comandos"], "location": "1.5 cun por encima del pliegue de la muñeca, sobre el estiloides radial.", "indications": ["resfriados", "cefalea occipital", "dolor cervical", "asma", "trastornos del CV"] },
    "LU8": { "code": "LU8", "meridian": "LU", "chinese": "經渠", "pinyin": "Jīng Qú", "spanish": "Canal del Río", "location": "—", "indications": [] },
    "LU9": { "code": "LU9", "meridian": "LU", "chinese": "太淵", "pinyin": "Tài Yuān", "spanish": "Abismo Supremo", "category": ["yuan", "shu-arroyo", "reunión de los vasos"], "location": "En el pliegue de la muñeca, lateral a la arteria radial.", "indications": ["disnea", "tos crónica", "asma", "trastornos vasculares", "dolor de muñeca"] },
    "LU10": { "code": "LU10", "meridian": "LU", "chinese": "魚際", "pinyin": "Yú Jì", "spanish": "Borde del Pez", "category": ["ying-manantial"], "location": "En la palma, en el centro del primer metacarpiano, en la línea de unión piel roja/blanca.", "indications": ["dolor de garganta", "fiebre", "tos seca"] },
    "LU11": { "code": "LU11", "meridian": "LU", "chinese": "少商", "pinyin": "Shào Shāng", "spanish": "Comerciante Menor", "category": ["jing-pozo"], "location": "Esquina ungueal radial del pulgar, 0.1 cun de la uña.", "indications": ["dolor de garganta agudo", "fiebre alta", "pérdida de consciencia"] },

    "LI1": { "code": "LI1", "meridian": "LI", "chinese": "商陽", "pinyin": "Shāng Yáng", "spanish": "Yang del Comerciante", "category": ["jing-pozo"], "location": "Esquina ungueal radial del índice.", "indications": ["fiebre", "dolor de garganta", "pérdida de consciencia"] },
    "LI2": { "code": "LI2", "meridian": "LI", "chinese": "二間", "pinyin": "Èr Jiān", "spanish": "Segundo Espacio", "location": "—", "indications": [] },
    "LI3": { "code": "LI3", "meridian": "LI", "chinese": "三間", "pinyin": "Sān Jiān", "spanish": "Tercer Espacio", "location": "—", "indications": [] },
    "LI4": { "code": "LI4", "meridian": "LI", "chinese": "合谷", "pinyin": "Hé Gǔ", "spanish": "Unión del Valle", "category": ["yuan", "uno de los 4 comandos (cara)"], "location": "En el dorso de la mano, en el punto medio del segundo metacarpiano, en su borde radial.", "indications": ["cefalea", "resfriado", "dolor dental", "rinitis", "amenorrea (contraindicado en embarazo)"] },
    "LI5": { "code": "LI5", "meridian": "LI", "chinese": "陽谿", "pinyin": "Yáng Xī", "spanish": "Arroyo Yang", "location": "—", "indications": [] },
    "LI6": { "code": "LI6", "meridian": "LI", "chinese": "偏歷", "pinyin": "Piān Lì", "spanish": "Paso Lateral", "category": ["luo"], "location": "—", "indications": [] },
    "LI7": { "code": "LI7", "meridian": "LI", "chinese": "溫溜", "pinyin": "Wēn Liū", "spanish": "Caudal Tibio", "location": "—", "indications": [] },
    "LI8": { "code": "LI8", "meridian": "LI", "chinese": "下廉", "pinyin": "Xià Lián", "spanish": "Borde Inferior", "location": "—", "indications": [] },
    "LI9": { "code": "LI9", "meridian": "LI", "chinese": "上廉", "pinyin": "Shàng Lián", "spanish": "Borde Superior", "location": "—", "indications": [] },
    "LI10": { "code": "LI10", "meridian": "LI", "chinese": "手三里", "pinyin": "Shǒu Sān Lǐ", "spanish": "Tres Distancias del Brazo", "location": "—", "indications": [] },
    "LI11": { "code": "LI11", "meridian": "LI", "chinese": "曲池", "pinyin": "Qū Chí", "spanish": "Estanque Curvo", "category": ["he-mar"], "location": "En la depresión externa del codo, a medio camino entre LU5 y el epicóndilo lateral, con el codo flexionado.", "indications": ["fiebre", "hipertensión", "afecciones cutáneas", "estreñimiento", "dolor de codo"] },
    "LI12": { "code": "LI12", "meridian": "LI", "chinese": "肘髎", "pinyin": "Zhǒu Liáo", "spanish": "Hueso del Codo", "location": "—", "indications": [] },
    "LI13": { "code": "LI13", "meridian": "LI", "chinese": "手五里", "pinyin": "Shǒu Wǔ Lǐ", "spanish": "Cinco Distancias del Brazo", "location": "—", "indications": [] },
    "LI14": { "code": "LI14", "meridian": "LI", "chinese": "臂臑", "pinyin": "Bì Nào", "spanish": "Brazo y Húmero", "location": "—", "indications": [] },
    "LI15": { "code": "LI15", "meridian": "LI", "chinese": "肩髃", "pinyin": "Jiān Yú", "spanish": "Hueso del Hombro", "location": "—", "indications": ["dolor de hombro", "parálisis del miembro superior"] },
    "LI16": { "code": "LI16", "meridian": "LI", "chinese": "巨骨", "pinyin": "Jù Gǔ", "spanish": "Hueso Grande", "location": "—", "indications": [] },
    "LI17": { "code": "LI17", "meridian": "LI", "chinese": "天鼎", "pinyin": "Tiān Dǐng", "spanish": "Trípode Celestial", "location": "—", "indications": [] },
    "LI18": { "code": "LI18", "meridian": "LI", "chinese": "扶突", "pinyin": "Fú Tū", "spanish": "Apoyo Saliente", "location": "—", "indications": [] },
    "LI19": { "code": "LI19", "meridian": "LI", "chinese": "口禾髎", "pinyin": "Kǒu Hé Liáo", "spanish": "Hueso del Cereal de la Boca", "location": "—", "indications": [] },
    "LI20": { "code": "LI20", "meridian": "LI", "chinese": "迎香", "pinyin": "Yíng Xiāng", "spanish": "Bienvenida Fragante", "location": "En el surco nasolabial, junto al ala de la nariz.", "indications": ["congestión nasal", "rinitis", "sinusitis", "parálisis facial"] },

    "ST1": { "code": "ST1", "meridian": "ST", "chinese": "承泣", "pinyin": "Chéng Qì", "spanish": "Receptor de Lágrimas", "location": "—", "indications": [] },
    "ST2": { "code": "ST2", "meridian": "ST", "chinese": "四白", "pinyin": "Sì Bái", "spanish": "Cuatro Blancos", "location": "—", "indications": [] },
    "ST3": { "code": "ST3", "meridian": "ST", "chinese": "巨髎", "pinyin": "Jù Liáo", "spanish": "Hueso Grande Facial", "location": "—", "indications": [] },
    "ST4": { "code": "ST4", "meridian": "ST", "chinese": "地倉", "pinyin": "Dì Cāng", "spanish": "Almacén de la Tierra", "location": "—", "indications": [] },
    "ST5": { "code": "ST5", "meridian": "ST", "chinese": "大迎", "pinyin": "Dà Yíng", "spanish": "Gran Bienvenida", "location": "—", "indications": [] },
    "ST6": { "code": "ST6", "meridian": "ST", "chinese": "頰車", "pinyin": "Jiá Chē", "spanish": "Carro de la Mejilla", "location": "—", "indications": ["bruxismo", "neuralgia del trigémino", "ATM"] },
    "ST7": { "code": "ST7", "meridian": "ST", "chinese": "下關", "pinyin": "Xià Guān", "spanish": "Paso Inferior", "location": "—", "indications": [] },
    "ST8": { "code": "ST8", "meridian": "ST", "chinese": "頭維", "pinyin": "Tóu Wéi", "spanish": "Esquina de la Cabeza", "location": "—", "indications": [] },
    "ST9": { "code": "ST9", "meridian": "ST", "chinese": "人迎", "pinyin": "Rén Yíng", "spanish": "Bienvenida del Hombre", "location": "—", "indications": [] },
    "ST10": { "code": "ST10", "meridian": "ST", "chinese": "水突", "pinyin": "Shuǐ Tū", "spanish": "Saliente del Agua", "location": "—", "indications": [] },
    "ST11": { "code": "ST11", "meridian": "ST", "chinese": "氣舍", "pinyin": "Qì Shè", "spanish": "Morada del Qi", "location": "—", "indications": [] },
    "ST12": { "code": "ST12", "meridian": "ST", "chinese": "缺盆", "pinyin": "Quē Pén", "spanish": "Cuenco Roto", "location": "—", "indications": [] },
    "ST13": { "code": "ST13", "meridian": "ST", "chinese": "氣戶", "pinyin": "Qì Hù", "spanish": "Puerta del Qi", "location": "—", "indications": [] },
    "ST14": { "code": "ST14", "meridian": "ST", "chinese": "庫房", "pinyin": "Kù Fáng", "spanish": "Sala del Almacén", "location": "—", "indications": [] },
    "ST15": { "code": "ST15", "meridian": "ST", "chinese": "屋翳", "pinyin": "Wū Yì", "spanish": "Cobijo del Hogar", "location": "—", "indications": [] },
    "ST16": { "code": "ST16", "meridian": "ST", "chinese": "膺窗", "pinyin": "Yīng Chuāng", "spanish": "Ventana del Pecho", "location": "—", "indications": [] },
    "ST17": { "code": "ST17", "meridian": "ST", "chinese": "乳中", "pinyin": "Rǔ Zhōng", "spanish": "Centro del Pezón", "location": "Centro del pezón. Sólo para localización (no se puntura).", "indications": [] },
    "ST18": { "code": "ST18", "meridian": "ST", "chinese": "乳根", "pinyin": "Rǔ Gēn", "spanish": "Raíz del Pecho", "location": "—", "indications": [] },
    "ST19": { "code": "ST19", "meridian": "ST", "chinese": "不容", "pinyin": "Bù Róng", "spanish": "Sin Cabida", "location": "—", "indications": [] },
    "ST20": { "code": "ST20", "meridian": "ST", "chinese": "承滿", "pinyin": "Chéng Mǎn", "spanish": "Receptor de la Plenitud", "location": "—", "indications": [] },
    "ST21": { "code": "ST21", "meridian": "ST", "chinese": "梁門", "pinyin": "Liáng Mén", "spanish": "Puerta del Dintel", "location": "—", "indications": [] },
    "ST22": { "code": "ST22", "meridian": "ST", "chinese": "關門", "pinyin": "Guān Mén", "spanish": "Puerta del Paso", "location": "—", "indications": [] },
    "ST23": { "code": "ST23", "meridian": "ST", "chinese": "太乙", "pinyin": "Tài Yǐ", "spanish": "Gran Misterio", "location": "—", "indications": [] },
    "ST24": { "code": "ST24", "meridian": "ST", "chinese": "滑肉門", "pinyin": "Huá Ròu Mén", "spanish": "Puerta de la Carne Lisa", "location": "—", "indications": [] },
    "ST25": { "code": "ST25", "meridian": "ST", "chinese": "天樞", "pinyin": "Tiān Shū", "spanish": "Eje Celestial", "category": ["mu del Intestino Grueso"], "location": "2 cun lateral al ombligo.", "indications": ["estreñimiento", "diarrea", "dolor abdominal", "menstruación irregular"] },
    "ST26": { "code": "ST26", "meridian": "ST", "chinese": "外陵", "pinyin": "Wài Líng", "spanish": "Colina Exterior", "location": "—", "indications": [] },
    "ST27": { "code": "ST27", "meridian": "ST", "chinese": "大巨", "pinyin": "Dà Jù", "spanish": "Gran Eminencia", "location": "—", "indications": [] },
    "ST28": { "code": "ST28", "meridian": "ST", "chinese": "水道", "pinyin": "Shuǐ Dào", "spanish": "Vía del Agua", "location": "—", "indications": [] },
    "ST29": { "code": "ST29", "meridian": "ST", "chinese": "歸來", "pinyin": "Guī Lái", "spanish": "Volver al Hogar", "location": "—", "indications": [] },
    "ST30": { "code": "ST30", "meridian": "ST", "chinese": "氣衝", "pinyin": "Qì Chōng", "spanish": "Asalto del Qi", "location": "—", "indications": [] },
    "ST31": { "code": "ST31", "meridian": "ST", "chinese": "髀關", "pinyin": "Bì Guān", "spanish": "Paso del Fémur", "location": "—", "indications": [] },
    "ST32": { "code": "ST32", "meridian": "ST", "chinese": "伏兔", "pinyin": "Fú Tù", "spanish": "Liebre Agachada", "location": "—", "indications": [] },
    "ST33": { "code": "ST33", "meridian": "ST", "chinese": "陰市", "pinyin": "Yīn Shì", "spanish": "Mercado del Yin", "location": "—", "indications": [] },
    "ST34": { "code": "ST34", "meridian": "ST", "chinese": "梁丘", "pinyin": "Liáng Qiū", "spanish": "Loma del Dintel", "category": ["xi-acumulación"], "location": "2 cun proximal al ángulo súpero-lateral de la rótula.", "indications": ["dolor agudo de estómago", "dolor de rodilla"] },
    "ST35": { "code": "ST35", "meridian": "ST", "chinese": "犢鼻", "pinyin": "Dú Bí", "spanish": "Nariz de Ternero", "location": "Depresión lateral al tendón rotuliano, con la rodilla flexionada.", "indications": ["dolor de rodilla"] },
    "ST36": { "code": "ST36", "meridian": "ST", "chinese": "足三里", "pinyin": "Zú Sān Lǐ", "spanish": "Tres Distancias de la Pierna", "category": ["he-mar", "uno de los 4 comandos (abdomen)"], "location": "3 cun por debajo de ST35, un dedo lateral al borde anterior de la tibia.", "indications": ["fatiga crónica", "deficiencia general", "trastornos digestivos", "refuerzo del sistema inmune (punto tonificante por excelencia)"] },
    "ST37": { "code": "ST37", "meridian": "ST", "chinese": "上巨虛", "pinyin": "Shàng Jù Xū", "spanish": "Gran Vacío Superior", "category": ["he inferior del Intestino Grueso"], "location": "—", "indications": [] },
    "ST38": { "code": "ST38", "meridian": "ST", "chinese": "條口", "pinyin": "Tiáo Kǒu", "spanish": "Línea de Apertura", "location": "—", "indications": ["hombro congelado"] },
    "ST39": { "code": "ST39", "meridian": "ST", "chinese": "下巨虛", "pinyin": "Xià Jù Xū", "spanish": "Gran Vacío Inferior", "category": ["he inferior del Intestino Delgado"], "location": "—", "indications": [] },
    "ST40": { "code": "ST40", "meridian": "ST", "chinese": "豐隆", "pinyin": "Fēng Lóng", "spanish": "Abundante Plenitud", "category": ["luo"], "location": "Punto medio entre ST35 y el maléolo externo, 2 cun lateral a la cresta tibial.", "indications": ["mucosidad/flemas (físicas y mentales)", "obesidad", "vértigo", "psiquismo enturbiado por humedad"] },
    "ST41": { "code": "ST41", "meridian": "ST", "chinese": "解谿", "pinyin": "Jiě Xī", "spanish": "Arroyo Liberado", "location": "—", "indications": [] },
    "ST42": { "code": "ST42", "meridian": "ST", "chinese": "衝陽", "pinyin": "Chōng Yáng", "spanish": "Yang Asaltante", "category": ["yuan"], "location": "—", "indications": [] },
    "ST43": { "code": "ST43", "meridian": "ST", "chinese": "陷谷", "pinyin": "Xiàn Gǔ", "spanish": "Valle Hundido", "location": "—", "indications": [] },
    "ST44": { "code": "ST44", "meridian": "ST", "chinese": "內庭", "pinyin": "Nèi Tíng", "spanish": "Patio Interior", "category": ["ying-manantial"], "location": "Entre el 2º y 3º dedo del pie, en la unión piel roja/blanca.", "indications": ["dolor dental superior", "calor de estómago", "epistaxis"] },
    "ST45": { "code": "ST45", "meridian": "ST", "chinese": "厲兌", "pinyin": "Lì Duì", "spanish": "Intercambio Severo", "category": ["jing-pozo"], "location": "—", "indications": [] },

    "SP1": { "code": "SP1", "meridian": "SP", "chinese": "隱白", "pinyin": "Yǐn Bái", "spanish": "Blanco Oculto", "category": ["jing-pozo"], "location": "Esquina ungueal medial del primer dedo del pie.", "indications": ["sangrado uterino", "pesadillas"] },
    "SP2": { "code": "SP2", "meridian": "SP", "chinese": "大都", "pinyin": "Dà Dū", "spanish": "Gran Capital", "location": "—", "indications": [] },
    "SP3": { "code": "SP3", "meridian": "SP", "chinese": "太白", "pinyin": "Tài Bái", "spanish": "Blanco Supremo", "category": ["yuan"], "location": "—", "indications": [] },
    "SP4": { "code": "SP4", "meridian": "SP", "chinese": "公孫", "pinyin": "Gōng Sūn", "spanish": "Abuelo Nieto", "category": ["luo", "comando del Chong Mai"], "location": "En el lado medial del pie, en la base del primer metatarsiano.", "indications": ["dolor abdominal", "trastornos menstruales", "abrir Chong Mai"] },
    "SP5": { "code": "SP5", "meridian": "SP", "chinese": "商丘", "pinyin": "Shāng Qiū", "spanish": "Loma del Comerciante", "location": "—", "indications": [] },
    "SP6": { "code": "SP6", "meridian": "SP", "chinese": "三陰交", "pinyin": "Sān Yīn Jiāo", "spanish": "Cruce de los Tres Yin", "category": ["cruce SP-LV-KI"], "location": "3 cun por encima del maléolo interno, en el borde posterior de la tibia.", "indications": ["trastornos menstruales y ginecológicos", "insomnio", "deficiencia del Yin", "contraindicado en embarazo"] },
    "SP7": { "code": "SP7", "meridian": "SP", "chinese": "漏谷", "pinyin": "Lòu Gǔ", "spanish": "Valle de la Filtración", "location": "—", "indications": [] },
    "SP8": { "code": "SP8", "meridian": "SP", "chinese": "地機", "pinyin": "Dì Jī", "spanish": "Mecanismo de la Tierra", "category": ["xi-acumulación"], "location": "—", "indications": ["dismenorrea aguda"] },
    "SP9": { "code": "SP9", "meridian": "SP", "chinese": "陰陵泉", "pinyin": "Yīn Líng Quán", "spanish": "Fuente de la Colina Yin", "category": ["he-mar"], "location": "Bajo el cóndilo medial de la tibia, en la depresión.", "indications": ["edema", "humedad y mucosidades", "trastornos urinarios", "dolor de rodilla interna"] },
    "SP10": { "code": "SP10", "meridian": "SP", "chinese": "血海", "pinyin": "Xuè Hǎi", "spanish": "Mar de la Sangre", "location": "2 cun por encima del borde superior medial de la rótula.", "indications": ["trastornos ginecológicos por sangre", "afecciones cutáneas pruriginosas", "menstruación irregular"] },
    "SP11": { "code": "SP11", "meridian": "SP", "chinese": "箕門", "pinyin": "Jī Mén", "spanish": "Puerta del Aventador", "location": "—", "indications": [] },
    "SP12": { "code": "SP12", "meridian": "SP", "chinese": "衝門", "pinyin": "Chōng Mén", "spanish": "Puerta del Asalto", "location": "—", "indications": [] },
    "SP13": { "code": "SP13", "meridian": "SP", "chinese": "府舍", "pinyin": "Fǔ Shè", "spanish": "Morada del Palacio", "location": "—", "indications": [] },
    "SP14": { "code": "SP14", "meridian": "SP", "chinese": "腹結", "pinyin": "Fù Jié", "spanish": "Nudo Abdominal", "location": "—", "indications": [] },
    "SP15": { "code": "SP15", "meridian": "SP", "chinese": "大橫", "pinyin": "Dà Héng", "spanish": "Gran Horizontal", "location": "—", "indications": [] },
    "SP16": { "code": "SP16", "meridian": "SP", "chinese": "腹哀", "pinyin": "Fù Āi", "spanish": "Lamento Abdominal", "location": "—", "indications": [] },
    "SP17": { "code": "SP17", "meridian": "SP", "chinese": "食竇", "pinyin": "Shí Dòu", "spanish": "Cavidad de la Comida", "location": "—", "indications": [] },
    "SP18": { "code": "SP18", "meridian": "SP", "chinese": "天谿", "pinyin": "Tiān Xī", "spanish": "Arroyo Celestial", "location": "—", "indications": [] },
    "SP19": { "code": "SP19", "meridian": "SP", "chinese": "胸鄉", "pinyin": "Xiōng Xiāng", "spanish": "Aldea del Pecho", "location": "—", "indications": [] },
    "SP20": { "code": "SP20", "meridian": "SP", "chinese": "周榮", "pinyin": "Zhōu Róng", "spanish": "Gloria que Rodea", "location": "—", "indications": [] },
    "SP21": { "code": "SP21", "meridian": "SP", "chinese": "大包", "pinyin": "Dà Bāo", "spanish": "Gran Envoltura", "category": ["gran luo del bazo"], "location": "Línea axilar media, 6º espacio intercostal.", "indications": ["fatiga generalizada", "dolor de todo el cuerpo"] },

    "HT1": { "code": "HT1", "meridian": "HT", "chinese": "極泉", "pinyin": "Jí Quán", "spanish": "Fuente Suprema", "location": "—", "indications": [] },
    "HT2": { "code": "HT2", "meridian": "HT", "chinese": "青靈", "pinyin": "Qīng Líng", "spanish": "Espíritu Verde", "location": "—", "indications": [] },
    "HT3": { "code": "HT3", "meridian": "HT", "chinese": "少海", "pinyin": "Shào Hǎi", "spanish": "Mar Menor", "category": ["he-mar"], "location": "—", "indications": [] },
    "HT4": { "code": "HT4", "meridian": "HT", "chinese": "靈道", "pinyin": "Líng Dào", "spanish": "Vía del Espíritu", "location": "—", "indications": [] },
    "HT5": { "code": "HT5", "meridian": "HT", "chinese": "通里", "pinyin": "Tōng Lǐ", "spanish": "Comunicación Interior", "category": ["luo"], "location": "—", "indications": ["palpitaciones", "afasia"] },
    "HT6": { "code": "HT6", "meridian": "HT", "chinese": "陰郄", "pinyin": "Yīn Xī", "spanish": "Hendidura Yin", "category": ["xi-acumulación"], "location": "—", "indications": ["sudoración nocturna"] },
    "HT7": { "code": "HT7", "meridian": "HT", "chinese": "神門", "pinyin": "Shén Mén", "spanish": "Puerta del Espíritu", "category": ["yuan", "shu-arroyo"], "location": "Pliegue de la muñeca, lateral al pisiforme, en el lado cubital.", "indications": ["insomnio", "ansiedad", "palpitaciones", "agitación del shen", "memoria"] },
    "HT8": { "code": "HT8", "meridian": "HT", "chinese": "少府", "pinyin": "Shào Fǔ", "spanish": "Palacio Menor", "category": ["ying-manantial"], "location": "—", "indications": [] },
    "HT9": { "code": "HT9", "meridian": "HT", "chinese": "少衝", "pinyin": "Shào Chōng", "spanish": "Asalto Menor", "category": ["jing-pozo"], "location": "Esquina ungueal radial del meñique.", "indications": ["pérdida de consciencia", "fiebre alta"] },

    "SI1": { "code": "SI1", "meridian": "SI", "chinese": "少澤", "pinyin": "Shào Zé", "spanish": "Pantano Menor", "category": ["jing-pozo"], "location": "Esquina ungueal cubital del meñique.", "indications": ["agalactia (estimular lactancia)"] },
    "SI2": { "code": "SI2", "meridian": "SI", "chinese": "前谷", "pinyin": "Qián Gǔ", "spanish": "Valle Anterior", "location": "—", "indications": [] },
    "SI3": { "code": "SI3", "meridian": "SI", "chinese": "後谿", "pinyin": "Hòu Xī", "spanish": "Arroyo Posterior", "category": ["shu-arroyo", "comando del Du Mai"], "location": "Lado cubital de la mano, distal a la cabeza del 5º metacarpiano, con el puño cerrado.", "indications": ["dolor cervical", "dolor lumbar", "trastornos del Du Mai", "rigidez de columna"] },
    "SI4": { "code": "SI4", "meridian": "SI", "chinese": "腕骨", "pinyin": "Wàn Gǔ", "spanish": "Hueso de la Muñeca", "category": ["yuan"], "location": "—", "indications": [] },
    "SI5": { "code": "SI5", "meridian": "SI", "chinese": "陽谷", "pinyin": "Yáng Gǔ", "spanish": "Valle Yang", "location": "—", "indications": [] },
    "SI6": { "code": "SI6", "meridian": "SI", "chinese": "養老", "pinyin": "Yǎng Lǎo", "spanish": "Cuidado del Anciano", "category": ["xi-acumulación"], "location": "—", "indications": ["disminución de visión", "rigidez cervical en mayores"] },
    "SI7": { "code": "SI7", "meridian": "SI", "chinese": "支正", "pinyin": "Zhī Zhèng", "spanish": "Rama Recta", "category": ["luo"], "location": "—", "indications": [] },
    "SI8": { "code": "SI8", "meridian": "SI", "chinese": "小海", "pinyin": "Xiǎo Hǎi", "spanish": "Mar Pequeño", "category": ["he-mar"], "location": "—", "indications": [] },
    "SI9": { "code": "SI9", "meridian": "SI", "chinese": "肩貞", "pinyin": "Jiān Zhēn", "spanish": "Hombro Recto", "location": "—", "indications": [] },
    "SI10": { "code": "SI10", "meridian": "SI", "chinese": "臑俞", "pinyin": "Nào Shū", "spanish": "Punto Shu del Húmero", "location": "—", "indications": [] },
    "SI11": { "code": "SI11", "meridian": "SI", "chinese": "天宗", "pinyin": "Tiān Zōng", "spanish": "Antepasado Celestial", "location": "Centro de la fosa infraespinosa de la escápula.", "indications": ["dolor de hombro", "tensión escapular"] },
    "SI12": { "code": "SI12", "meridian": "SI", "chinese": "秉風", "pinyin": "Bǐng Fēng", "spanish": "Sostén del Viento", "location": "—", "indications": [] },
    "SI13": { "code": "SI13", "meridian": "SI", "chinese": "曲垣", "pinyin": "Qū Yuán", "spanish": "Muro Curvo", "location": "—", "indications": [] },
    "SI14": { "code": "SI14", "meridian": "SI", "chinese": "肩外俞", "pinyin": "Jiān Wài Shū", "spanish": "Punto Shu del Hombro Exterior", "location": "—", "indications": [] },
    "SI15": { "code": "SI15", "meridian": "SI", "chinese": "肩中俞", "pinyin": "Jiān Zhōng Shū", "spanish": "Punto Shu Central del Hombro", "location": "—", "indications": [] },
    "SI16": { "code": "SI16", "meridian": "SI", "chinese": "天窗", "pinyin": "Tiān Chuāng", "spanish": "Ventana Celestial", "location": "—", "indications": [] },
    "SI17": { "code": "SI17", "meridian": "SI", "chinese": "天容", "pinyin": "Tiān Róng", "spanish": "Apariencia Celestial", "location": "—", "indications": [] },
    "SI18": { "code": "SI18", "meridian": "SI", "chinese": "顴髎", "pinyin": "Quán Liáo", "spanish": "Hueso del Pómulo", "location": "—", "indications": [] },
    "SI19": { "code": "SI19", "meridian": "SI", "chinese": "聽宮", "pinyin": "Tīng Gōng", "spanish": "Palacio del Oído", "location": "—", "indications": ["acúfenos", "hipoacusia"] },

    "BL1": { "code": "BL1", "meridian": "BL", "chinese": "睛明", "pinyin": "Jīng Míng", "spanish": "Brillo de la Pupila", "location": "Borde interno del ojo, en el ángulo orbital nasal.", "indications": ["trastornos oculares en general"] },
    "BL2": { "code": "BL2", "meridian": "BL", "chinese": "攢竹", "pinyin": "Zǎn Zhú", "spanish": "Bambú Acumulado", "location": "—", "indications": [] },
    "BL3": { "code": "BL3", "meridian": "BL", "chinese": "眉衝", "pinyin": "Méi Chōng", "spanish": "Choque de Ceja", "location": "—", "indications": [] },
    "BL4": { "code": "BL4", "meridian": "BL", "chinese": "曲差", "pinyin": "Qū Chā", "spanish": "Curva Diferenciada", "location": "—", "indications": [] },
    "BL5": { "code": "BL5", "meridian": "BL", "chinese": "五處", "pinyin": "Wǔ Chù", "spanish": "Cinco Lugares", "location": "—", "indications": [] },
    "BL6": { "code": "BL6", "meridian": "BL", "chinese": "承光", "pinyin": "Chéng Guāng", "spanish": "Receptor de Luz", "location": "—", "indications": [] },
    "BL7": { "code": "BL7", "meridian": "BL", "chinese": "通天", "pinyin": "Tōng Tiān", "spanish": "Conexión Celeste", "location": "—", "indications": [] },
    "BL8": { "code": "BL8", "meridian": "BL", "chinese": "絡卻", "pinyin": "Luò Què", "spanish": "Declive del Luo", "location": "—", "indications": [] },
    "BL9": { "code": "BL9", "meridian": "BL", "chinese": "玉枕", "pinyin": "Yù Zhěn", "spanish": "Almohada de Jade", "location": "—", "indications": [] },
    "BL10": { "code": "BL10", "meridian": "BL", "chinese": "天柱", "pinyin": "Tiān Zhù", "spanish": "Columna Celestial", "location": "Borde lateral del trapecio, 1.3 cun lateral a GV15.", "indications": ["cefalea occipital", "dolor cervical", "rigidez cervical"] },
    "BL11": { "code": "BL11", "meridian": "BL", "chinese": "大杼", "pinyin": "Dà Zhù", "spanish": "Gran Lanzadera", "category": ["reunión de los huesos"], "location": "—", "indications": [] },
    "BL12": { "code": "BL12", "meridian": "BL", "chinese": "風門", "pinyin": "Fēng Mén", "spanish": "Puerta del Viento", "location": "—", "indications": ["resfriados", "rigidez cervical-dorsal alta"] },
    "BL13": { "code": "BL13", "meridian": "BL", "chinese": "肺俞", "pinyin": "Fèi Shū", "spanish": "Shu del Pulmón", "category": ["shu de espalda del Pulmón"], "location": "1.5 cun lateral al borde inferior de la apófisis espinosa de T3.", "indications": ["asma", "tos", "enfermedades respiratorias crónicas"] },
    "BL14": { "code": "BL14", "meridian": "BL", "chinese": "厥陰俞", "pinyin": "Jué Yīn Shū", "spanish": "Shu del Jueyin (Pericardio)", "category": ["shu de espalda del Pericardio"], "location": "—", "indications": [] },
    "BL15": { "code": "BL15", "meridian": "BL", "chinese": "心俞", "pinyin": "Xīn Shū", "spanish": "Shu del Corazón", "category": ["shu de espalda del Corazón"], "location": "1.5 cun lateral a T5.", "indications": ["palpitaciones", "ansiedad", "insomnio"] },
    "BL16": { "code": "BL16", "meridian": "BL", "chinese": "督俞", "pinyin": "Dū Shū", "spanish": "Shu del Du Mai", "location": "—", "indications": [] },
    "BL17": { "code": "BL17", "meridian": "BL", "chinese": "膈俞", "pinyin": "Gé Shū", "spanish": "Shu del Diafragma", "category": ["reunión de la sangre"], "location": "1.5 cun lateral a T7.", "indications": ["trastornos de la sangre", "hipo persistente"] },
    "BL18": { "code": "BL18", "meridian": "BL", "chinese": "肝俞", "pinyin": "Gān Shū", "spanish": "Shu del Hígado", "category": ["shu de espalda del Hígado"], "location": "1.5 cun lateral a T9.", "indications": ["trastornos hepáticos", "ojos", "frustración crónica"] },
    "BL19": { "code": "BL19", "meridian": "BL", "chinese": "膽俞", "pinyin": "Dǎn Shū", "spanish": "Shu de la Vesícula", "category": ["shu de espalda de la Vesícula"], "location": "—", "indications": [] },
    "BL20": { "code": "BL20", "meridian": "BL", "chinese": "脾俞", "pinyin": "Pí Shū", "spanish": "Shu del Bazo", "category": ["shu de espalda del Bazo"], "location": "1.5 cun lateral a T11.", "indications": ["digestiones débiles", "fatiga", "humedad"] },
    "BL21": { "code": "BL21", "meridian": "BL", "chinese": "胃俞", "pinyin": "Wèi Shū", "spanish": "Shu del Estómago", "category": ["shu de espalda del Estómago"], "location": "—", "indications": [] },
    "BL22": { "code": "BL22", "meridian": "BL", "chinese": "三焦俞", "pinyin": "Sān Jiāo Shū", "spanish": "Shu del Triple Calentador", "location": "—", "indications": [] },
    "BL23": { "code": "BL23", "meridian": "BL", "chinese": "腎俞", "pinyin": "Shèn Shū", "spanish": "Shu del Riñón", "category": ["shu de espalda del Riñón"], "location": "1.5 cun lateral a L2.", "indications": ["lumbalgia crónica", "tinnitus", "fatiga", "deficiencia de Riñón"] },
    "BL24": { "code": "BL24", "meridian": "BL", "chinese": "氣海俞", "pinyin": "Qì Hǎi Shū", "spanish": "Shu del Mar de Qi", "location": "—", "indications": [] },
    "BL25": { "code": "BL25", "meridian": "BL", "chinese": "大腸俞", "pinyin": "Dà Cháng Shū", "spanish": "Shu del Intestino Grueso", "location": "—", "indications": ["lumbalgia", "estreñimiento", "diarrea"] },
    "BL26": { "code": "BL26", "meridian": "BL", "chinese": "關元俞", "pinyin": "Guān Yuán Shū", "spanish": "Shu de Guan Yuan", "location": "—", "indications": [] },
    "BL27": { "code": "BL27", "meridian": "BL", "chinese": "小腸俞", "pinyin": "Xiǎo Cháng Shū", "spanish": "Shu del Intestino Delgado", "location": "—", "indications": [] },
    "BL28": { "code": "BL28", "meridian": "BL", "chinese": "膀胱俞", "pinyin": "Páng Guāng Shū", "spanish": "Shu de la Vejiga", "location": "—", "indications": [] },
    "BL29": { "code": "BL29", "meridian": "BL", "chinese": "中膂俞", "pinyin": "Zhōng Lǚ Shū", "spanish": "Shu Central de la Espalda", "location": "—", "indications": [] },
    "BL30": { "code": "BL30", "meridian": "BL", "chinese": "白環俞", "pinyin": "Bái Huán Shū", "spanish": "Shu del Anillo Blanco", "location": "—", "indications": [] },
    "BL31": { "code": "BL31", "meridian": "BL", "chinese": "上髎", "pinyin": "Shàng Liáo", "spanish": "Hueso Superior", "location": "—", "indications": [] },
    "BL32": { "code": "BL32", "meridian": "BL", "chinese": "次髎", "pinyin": "Cì Liáo", "spanish": "Hueso Secundario", "location": "—", "indications": ["dolor lumbar", "trastornos pélvicos"] },
    "BL33": { "code": "BL33", "meridian": "BL", "chinese": "中髎", "pinyin": "Zhōng Liáo", "spanish": "Hueso Central", "location": "—", "indications": [] },
    "BL34": { "code": "BL34", "meridian": "BL", "chinese": "下髎", "pinyin": "Xià Liáo", "spanish": "Hueso Inferior", "location": "—", "indications": [] },
    "BL35": { "code": "BL35", "meridian": "BL", "chinese": "會陽", "pinyin": "Huì Yáng", "spanish": "Reunión del Yang", "location": "—", "indications": [] },
    "BL36": { "code": "BL36", "meridian": "BL", "chinese": "承扶", "pinyin": "Chéng Fú", "spanish": "Soporte Receptor", "location": "—", "indications": [] },
    "BL37": { "code": "BL37", "meridian": "BL", "chinese": "殷門", "pinyin": "Yīn Mén", "spanish": "Puerta de la Prosperidad", "location": "—", "indications": [] },
    "BL38": { "code": "BL38", "meridian": "BL", "chinese": "浮郄", "pinyin": "Fú Xī", "spanish": "Hendidura Flotante", "location": "—", "indications": [] },
    "BL39": { "code": "BL39", "meridian": "BL", "chinese": "委陽", "pinyin": "Wěi Yáng", "spanish": "Yang Curvado", "category": ["he inferior del Triple Calentador"], "location": "—", "indications": [] },
    "BL40": { "code": "BL40", "meridian": "BL", "chinese": "委中", "pinyin": "Wěi Zhōng", "spanish": "Centro Curvado", "category": ["he-mar", "uno de los 4 comandos (lumbar)"], "location": "Punto medio del pliegue poplíteo.", "indications": ["lumbalgia (punto rey)", "ciática", "afecciones cutáneas calientes"] },
    "BL41": { "code": "BL41", "meridian": "BL", "chinese": "附分", "pinyin": "Fù Fēn", "spanish": "Rama Adjunta", "location": "—", "indications": [] },
    "BL42": { "code": "BL42", "meridian": "BL", "chinese": "魄戶", "pinyin": "Pò Hù", "spanish": "Puerta del Po", "location": "—", "indications": ["aspecto Po del Pulmón (instinto, sensación corporal)"] },
    "BL43": { "code": "BL43", "meridian": "BL", "chinese": "膏肓", "pinyin": "Gāo Huāng", "spanish": "Vital y Diafragma", "location": "—", "indications": ["enfermedades crónicas debilitantes", "gran tonificación"] },
    "BL44": { "code": "BL44", "meridian": "BL", "chinese": "神堂", "pinyin": "Shén Táng", "spanish": "Salón del Shen", "location": "—", "indications": [] },
    "BL45": { "code": "BL45", "meridian": "BL", "chinese": "譩譆", "pinyin": "Yī Xī", "spanish": "Suspiro", "location": "—", "indications": [] },
    "BL46": { "code": "BL46", "meridian": "BL", "chinese": "膈關", "pinyin": "Gé Guān", "spanish": "Paso del Diafragma", "location": "—", "indications": [] },
    "BL47": { "code": "BL47", "meridian": "BL", "chinese": "魂門", "pinyin": "Hún Mén", "spanish": "Puerta del Hun", "location": "—", "indications": ["aspecto Hun del Hígado (alma etérea, sueños)"] },
    "BL48": { "code": "BL48", "meridian": "BL", "chinese": "陽綱", "pinyin": "Yáng Gāng", "spanish": "Cuerda Yang", "location": "—", "indications": [] },
    "BL49": { "code": "BL49", "meridian": "BL", "chinese": "意舍", "pinyin": "Yì Shè", "spanish": "Morada del Yi", "location": "—", "indications": ["aspecto Yi del Bazo (intelecto)"] },
    "BL50": { "code": "BL50", "meridian": "BL", "chinese": "胃倉", "pinyin": "Wèi Cāng", "spanish": "Almacén del Estómago", "location": "—", "indications": [] },
    "BL51": { "code": "BL51", "meridian": "BL", "chinese": "肓門", "pinyin": "Huāng Mén", "spanish": "Puerta del Diafragma", "location": "—", "indications": [] },
    "BL52": { "code": "BL52", "meridian": "BL", "chinese": "志室", "pinyin": "Zhì Shì", "spanish": "Cámara del Zhi", "location": "—", "indications": ["aspecto Zhi del Riñón (voluntad)"] },
    "BL53": { "code": "BL53", "meridian": "BL", "chinese": "胞肓", "pinyin": "Bāo Huāng", "spanish": "Vital del Útero", "location": "—", "indications": [] },
    "BL54": { "code": "BL54", "meridian": "BL", "chinese": "秩邊", "pinyin": "Zhì Biān", "spanish": "Borde Ordenado", "location": "—", "indications": [] },
    "BL55": { "code": "BL55", "meridian": "BL", "chinese": "合陽", "pinyin": "Hé Yáng", "spanish": "Unión del Yang", "location": "—", "indications": [] },
    "BL56": { "code": "BL56", "meridian": "BL", "chinese": "承筋", "pinyin": "Chéng Jīn", "spanish": "Soporte de los Tendones", "location": "—", "indications": [] },
    "BL57": { "code": "BL57", "meridian": "BL", "chinese": "承山", "pinyin": "Chéng Shān", "spanish": "Soporte de la Montaña", "location": "Centro del gemelo, en la depresión cuando se contrae el músculo.", "indications": ["calambres en las pantorrillas", "lumbalgia", "hemorroides"] },
    "BL58": { "code": "BL58", "meridian": "BL", "chinese": "飛揚", "pinyin": "Fēi Yáng", "spanish": "Vuelo Elevado", "category": ["luo"], "location": "—", "indications": [] },
    "BL59": { "code": "BL59", "meridian": "BL", "chinese": "跗陽", "pinyin": "Fū Yáng", "spanish": "Yang del Empeine", "location": "—", "indications": [] },
    "BL60": { "code": "BL60", "meridian": "BL", "chinese": "崑崙", "pinyin": "Kūn Lún", "spanish": "Cordillera de Kunlun", "category": ["jing-río"], "location": "Entre el maléolo externo y el tendón de Aquiles.", "indications": ["dolor lumbar y de cuello", "cefalea", "parto difícil (contraindicado en embarazo)"] },
    "BL61": { "code": "BL61", "meridian": "BL", "chinese": "僕參", "pinyin": "Pú Cān", "spanish": "Subordinado en Visita", "location": "—", "indications": [] },
    "BL62": { "code": "BL62", "meridian": "BL", "chinese": "申脈", "pinyin": "Shēn Mài", "spanish": "Vaso Extendido", "category": ["comando del Yang Qiao"], "location": "Bajo el maléolo externo.", "indications": ["epilepsia", "trastornos del Yang Qiao", "insomnio"] },
    "BL63": { "code": "BL63", "meridian": "BL", "chinese": "金門", "pinyin": "Jīn Mén", "spanish": "Puerta de Oro", "category": ["xi-acumulación"], "location": "—", "indications": [] },
    "BL64": { "code": "BL64", "meridian": "BL", "chinese": "京骨", "pinyin": "Jīng Gǔ", "spanish": "Hueso de la Capital", "category": ["yuan"], "location": "—", "indications": [] },
    "BL65": { "code": "BL65", "meridian": "BL", "chinese": "束骨", "pinyin": "Shù Gǔ", "spanish": "Hueso Atado", "location": "—", "indications": [] },
    "BL66": { "code": "BL66", "meridian": "BL", "chinese": "足通谷", "pinyin": "Zú Tōng Gǔ", "spanish": "Valle de Comunicación del Pie", "location": "—", "indications": [] },
    "BL67": { "code": "BL67", "meridian": "BL", "chinese": "至陰", "pinyin": "Zhì Yīn", "spanish": "Llegada al Yin", "category": ["jing-pozo"], "location": "Esquina ungueal lateral del 5º dedo del pie.", "indications": ["malposición fetal (clásico)", "cefalea"] },

    "KI1": { "code": "KI1", "meridian": "KI", "chinese": "湧泉", "pinyin": "Yǒng Quán", "spanish": "Fuente Burbujeante", "category": ["jing-pozo"], "location": "En el tercio anterior de la planta del pie, en la depresión al cerrar los dedos.", "indications": ["pérdida de consciencia", "ansiedad aguda", "anclar el yin", "shock"] },
    "KI2": { "code": "KI2", "meridian": "KI", "chinese": "然谷", "pinyin": "Rán Gǔ", "spanish": "Valle de la Combustión", "category": ["ying-manantial"], "location": "—", "indications": [] },
    "KI3": { "code": "KI3", "meridian": "KI", "chinese": "太谿", "pinyin": "Tài Xī", "spanish": "Arroyo Supremo", "category": ["yuan", "shu-arroyo"], "location": "Entre el maléolo interno y el tendón de Aquiles.", "indications": ["deficiencia de Riñón yin o yang", "tinnitus", "lumbalgia crónica", "fatiga"] },
    "KI4": { "code": "KI4", "meridian": "KI", "chinese": "大鐘", "pinyin": "Dà Zhōng", "spanish": "Gran Campana", "category": ["luo"], "location": "—", "indications": [] },
    "KI5": { "code": "KI5", "meridian": "KI", "chinese": "水泉", "pinyin": "Shuǐ Quán", "spanish": "Fuente del Agua", "category": ["xi-acumulación"], "location": "—", "indications": ["amenorrea"] },
    "KI6": { "code": "KI6", "meridian": "KI", "chinese": "照海", "pinyin": "Zhào Hǎi", "spanish": "Mar Resplandeciente", "category": ["comando del Yin Qiao"], "location": "Bajo el maléolo interno.", "indications": ["sequedad", "garganta seca", "insomnio", "trastornos del Yin Qiao"] },
    "KI7": { "code": "KI7", "meridian": "KI", "chinese": "復溜", "pinyin": "Fù Liū", "spanish": "Flujo de Retorno", "category": ["jing-río"], "location": "—", "indications": ["edema", "sudoración nocturna"] },
    "KI8": { "code": "KI8", "meridian": "KI", "chinese": "交信", "pinyin": "Jiāo Xìn", "spanish": "Cruce de la Confianza", "location": "—", "indications": [] },
    "KI9": { "code": "KI9", "meridian": "KI", "chinese": "築賓", "pinyin": "Zhù Bīn", "spanish": "Huésped Constructor", "location": "—", "indications": ["intoxicaciones", "purificación emocional profunda"] },
    "KI10": { "code": "KI10", "meridian": "KI", "chinese": "陰谷", "pinyin": "Yīn Gǔ", "spanish": "Valle Yin", "category": ["he-mar"], "location": "—", "indications": [] },
    "KI11": { "code": "KI11", "meridian": "KI", "chinese": "橫骨", "pinyin": "Héng Gǔ", "spanish": "Hueso Horizontal", "location": "—", "indications": [] },
    "KI12": { "code": "KI12", "meridian": "KI", "chinese": "大赫", "pinyin": "Dà Hè", "spanish": "Gran Brillo", "location": "—", "indications": [] },
    "KI13": { "code": "KI13", "meridian": "KI", "chinese": "氣穴", "pinyin": "Qì Xué", "spanish": "Cueva del Qi", "location": "—", "indications": [] },
    "KI14": { "code": "KI14", "meridian": "KI", "chinese": "四滿", "pinyin": "Sì Mǎn", "spanish": "Cuatro Plenitudes", "location": "—", "indications": [] },
    "KI15": { "code": "KI15", "meridian": "KI", "chinese": "中注", "pinyin": "Zhōng Zhù", "spanish": "Vertido Central", "location": "—", "indications": [] },
    "KI16": { "code": "KI16", "meridian": "KI", "chinese": "肓俞", "pinyin": "Huāng Shū", "spanish": "Shu del Diafragma", "location": "—", "indications": [] },
    "KI17": { "code": "KI17", "meridian": "KI", "chinese": "商曲", "pinyin": "Shāng Qū", "spanish": "Curva del Comerciante", "location": "—", "indications": [] },
    "KI18": { "code": "KI18", "meridian": "KI", "chinese": "石關", "pinyin": "Shí Guān", "spanish": "Paso de Piedra", "location": "—", "indications": [] },
    "KI19": { "code": "KI19", "meridian": "KI", "chinese": "陰都", "pinyin": "Yīn Dū", "spanish": "Capital del Yin", "location": "—", "indications": [] },
    "KI20": { "code": "KI20", "meridian": "KI", "chinese": "腹通谷", "pinyin": "Fù Tōng Gǔ", "spanish": "Valle de Comunicación Abdominal", "location": "—", "indications": [] },
    "KI21": { "code": "KI21", "meridian": "KI", "chinese": "幽門", "pinyin": "Yōu Mén", "spanish": "Puerta Sombría", "location": "—", "indications": [] },
    "KI22": { "code": "KI22", "meridian": "KI", "chinese": "步廊", "pinyin": "Bù Láng", "spanish": "Galería del Paso", "location": "—", "indications": [] },
    "KI23": { "code": "KI23", "meridian": "KI", "chinese": "神封", "pinyin": "Shén Fēng", "spanish": "Sello del Espíritu", "location": "—", "indications": [] },
    "KI24": { "code": "KI24", "meridian": "KI", "chinese": "靈墟", "pinyin": "Líng Xū", "spanish": "Ruina del Espíritu", "location": "—", "indications": [] },
    "KI25": { "code": "KI25", "meridian": "KI", "chinese": "神藏", "pinyin": "Shén Cáng", "spanish": "Almacén del Espíritu", "location": "—", "indications": [] },
    "KI26": { "code": "KI26", "meridian": "KI", "chinese": "彧中", "pinyin": "Yù Zhōng", "spanish": "Centro Próspero", "location": "—", "indications": [] },
    "KI27": { "code": "KI27", "meridian": "KI", "chinese": "俞府", "pinyin": "Shū Fǔ", "spanish": "Palacio del Shu", "location": "—", "indications": [] },

    "PC1": { "code": "PC1", "meridian": "PC", "chinese": "天池", "pinyin": "Tiān Chí", "spanish": "Estanque Celestial", "location": "—", "indications": [] },
    "PC2": { "code": "PC2", "meridian": "PC", "chinese": "天泉", "pinyin": "Tiān Quán", "spanish": "Manantial Celestial", "location": "—", "indications": [] },
    "PC3": { "code": "PC3", "meridian": "PC", "chinese": "曲澤", "pinyin": "Qū Zé", "spanish": "Pantano Curvo", "category": ["he-mar"], "location": "—", "indications": [] },
    "PC4": { "code": "PC4", "meridian": "PC", "chinese": "郄門", "pinyin": "Xī Mén", "spanish": "Puerta de la Hendidura", "category": ["xi-acumulación"], "location": "—", "indications": ["palpitaciones agudas", "ansiedad aguda"] },
    "PC5": { "code": "PC5", "meridian": "PC", "chinese": "間使", "pinyin": "Jiān Shǐ", "spanish": "Mensajero Intermedio", "category": ["jing-río"], "location": "—", "indications": [] },
    "PC6": { "code": "PC6", "meridian": "PC", "chinese": "內關", "pinyin": "Nèi Guān", "spanish": "Paso Interno", "category": ["luo", "comando del Yin Wei"], "location": "2 cun por encima del pliegue de la muñeca, entre los tendones del palmar mayor y largo.", "indications": ["náuseas (incluido cinetosis y embarazo)", "ansiedad", "palpitaciones", "trastornos del Yin Wei"] },
    "PC7": { "code": "PC7", "meridian": "PC", "chinese": "大陵", "pinyin": "Dà Líng", "spanish": "Gran Túmulo", "category": ["yuan", "shu-arroyo"], "location": "—", "indications": [] },
    "PC8": { "code": "PC8", "meridian": "PC", "chinese": "勞宮", "pinyin": "Láo Gōng", "spanish": "Palacio del Trabajo", "category": ["ying-manantial"], "location": "Centro de la palma, entre los metacarpianos 2º y 3º.", "indications": ["úlceras bucales", "calor en el pecho", "sudoración palmar"] },
    "PC9": { "code": "PC9", "meridian": "PC", "chinese": "中衝", "pinyin": "Zhōng Chōng", "spanish": "Asalto Central", "category": ["jing-pozo"], "location": "Centro de la punta del dedo medio.", "indications": ["pérdida de consciencia", "shock"] },

    "TE1": { "code": "TE1", "meridian": "TE", "chinese": "關衝", "pinyin": "Guān Chōng", "spanish": "Asalto del Paso", "category": ["jing-pozo"], "location": "—", "indications": [] },
    "TE2": { "code": "TE2", "meridian": "TE", "chinese": "液門", "pinyin": "Yè Mén", "spanish": "Puerta de los Líquidos", "location": "—", "indications": [] },
    "TE3": { "code": "TE3", "meridian": "TE", "chinese": "中渚", "pinyin": "Zhōng Zhǔ", "spanish": "Banco Central", "category": ["shu-arroyo"], "location": "—", "indications": ["cefaleas temporales", "tinnitus"] },
    "TE4": { "code": "TE4", "meridian": "TE", "chinese": "陽池", "pinyin": "Yáng Chí", "spanish": "Estanque Yang", "category": ["yuan"], "location": "Pliegue dorsal de la muñeca, en la depresión entre los tendones extensores.", "indications": ["dolor de muñeca", "frialdad de manos"] },
    "TE5": { "code": "TE5", "meridian": "TE", "chinese": "外關", "pinyin": "Wài Guān", "spanish": "Paso Externo", "category": ["luo", "comando del Yang Wei"], "location": "2 cun por encima del pliegue dorsal de la muñeca, entre cúbito y radio.", "indications": ["resfriados", "rigidez cervical", "dolor lateral del cuerpo", "trastornos del Yang Wei"] },
    "TE6": { "code": "TE6", "meridian": "TE", "chinese": "支溝", "pinyin": "Zhī Gōu", "spanish": "Surco de la Rama", "category": ["jing-río"], "location": "—", "indications": ["estreñimiento crónico", "dolor costal"] },
    "TE7": { "code": "TE7", "meridian": "TE", "chinese": "會宗", "pinyin": "Huì Zōng", "spanish": "Reunión del Antepasado", "category": ["xi-acumulación"], "location": "—", "indications": [] },
    "TE8": { "code": "TE8", "meridian": "TE", "chinese": "三陽絡", "pinyin": "Sān Yáng Luò", "spanish": "Luo de los Tres Yang", "location": "—", "indications": [] },
    "TE9": { "code": "TE9", "meridian": "TE", "chinese": "四瀆", "pinyin": "Sì Dú", "spanish": "Cuatro Ríos", "location": "—", "indications": [] },
    "TE10": { "code": "TE10", "meridian": "TE", "chinese": "天井", "pinyin": "Tiān Jǐng", "spanish": "Pozo Celestial", "category": ["he-mar"], "location": "—", "indications": [] },
    "TE11": { "code": "TE11", "meridian": "TE", "chinese": "清冷淵", "pinyin": "Qīng Lěng Yuān", "spanish": "Abismo Frío y Claro", "location": "—", "indications": [] },
    "TE12": { "code": "TE12", "meridian": "TE", "chinese": "消濼", "pinyin": "Xiāo Luò", "spanish": "Disolución del Río", "location": "—", "indications": [] },
    "TE13": { "code": "TE13", "meridian": "TE", "chinese": "臑會", "pinyin": "Nào Huì", "spanish": "Reunión del Húmero", "location": "—", "indications": [] },
    "TE14": { "code": "TE14", "meridian": "TE", "chinese": "肩髎", "pinyin": "Jiān Liáo", "spanish": "Hueso del Hombro", "location": "—", "indications": ["dolor de hombro"] },
    "TE15": { "code": "TE15", "meridian": "TE", "chinese": "天髎", "pinyin": "Tiān Liáo", "spanish": "Hueso Celestial", "location": "—", "indications": [] },
    "TE16": { "code": "TE16", "meridian": "TE", "chinese": "天牖", "pinyin": "Tiān Yǒu", "spanish": "Ventana Celestial", "location": "—", "indications": [] },
    "TE17": { "code": "TE17", "meridian": "TE", "chinese": "翳風", "pinyin": "Yì Fēng", "spanish": "Pantalla del Viento", "location": "Detrás del lóbulo de la oreja, en la depresión entre la mandíbula y la apófisis mastoides.", "indications": ["acúfenos", "parálisis facial", "trastornos del oído"] },
    "TE18": { "code": "TE18", "meridian": "TE", "chinese": "瘛脈", "pinyin": "Chì Mài", "spanish": "Vaso Convulso", "location": "—", "indications": [] },
    "TE19": { "code": "TE19", "meridian": "TE", "chinese": "顱息", "pinyin": "Lú Xī", "spanish": "Reposo del Cráneo", "location": "—", "indications": [] },
    "TE20": { "code": "TE20", "meridian": "TE", "chinese": "角孫", "pinyin": "Jiǎo Sūn", "spanish": "Esquina del Antepasado", "location": "—", "indications": [] },
    "TE21": { "code": "TE21", "meridian": "TE", "chinese": "耳門", "pinyin": "Ěr Mén", "spanish": "Puerta del Oído", "location": "—", "indications": [] },
    "TE22": { "code": "TE22", "meridian": "TE", "chinese": "耳和髎", "pinyin": "Ěr Hé Liáo", "spanish": "Hueso de la Armonía del Oído", "location": "—", "indications": [] },
    "TE23": { "code": "TE23", "meridian": "TE", "chinese": "絲竹空", "pinyin": "Sī Zhú Kōng", "spanish": "Vacío del Bambú de Seda", "location": "Extremo lateral de la ceja.", "indications": ["cefalea temporal", "trastornos oculares", "tics palpebrales"] },

    "GB1": { "code": "GB1", "meridian": "GB", "chinese": "瞳子髎", "pinyin": "Tóng Zǐ Liáo", "spanish": "Hueso de la Pupila", "location": "—", "indications": [] },
    "GB2": { "code": "GB2", "meridian": "GB", "chinese": "聽會", "pinyin": "Tīng Huì", "spanish": "Reunión del Oído", "location": "—", "indications": [] },
    "GB3": { "code": "GB3", "meridian": "GB", "chinese": "上關", "pinyin": "Shàng Guān", "spanish": "Paso Superior", "location": "—", "indications": [] },
    "GB4": { "code": "GB4", "meridian": "GB", "chinese": "頷厭", "pinyin": "Hàn Yàn", "spanish": "Quijada Cansada", "location": "—", "indications": [] },
    "GB5": { "code": "GB5", "meridian": "GB", "chinese": "懸顱", "pinyin": "Xuán Lú", "spanish": "Cráneo Suspendido", "location": "—", "indications": [] },
    "GB6": { "code": "GB6", "meridian": "GB", "chinese": "懸釐", "pinyin": "Xuán Lí", "spanish": "Cabello Suspendido", "location": "—", "indications": [] },
    "GB7": { "code": "GB7", "meridian": "GB", "chinese": "曲鬢", "pinyin": "Qū Bìn", "spanish": "Sien Curva", "location": "—", "indications": [] },
    "GB8": { "code": "GB8", "meridian": "GB", "chinese": "率谷", "pinyin": "Shuài Gǔ", "spanish": "Valle Rector", "location": "—", "indications": ["cefalea temporal alcohólica"] },
    "GB9": { "code": "GB9", "meridian": "GB", "chinese": "天衝", "pinyin": "Tiān Chōng", "spanish": "Asalto Celestial", "location": "—", "indications": [] },
    "GB10": { "code": "GB10", "meridian": "GB", "chinese": "浮白", "pinyin": "Fú Bái", "spanish": "Blanco Flotante", "location": "—", "indications": [] },
    "GB11": { "code": "GB11", "meridian": "GB", "chinese": "頭竅陰", "pinyin": "Tóu Qiào Yīn", "spanish": "Yin de los Orificios de la Cabeza", "location": "—", "indications": [] },
    "GB12": { "code": "GB12", "meridian": "GB", "chinese": "完骨", "pinyin": "Wán Gǔ", "spanish": "Hueso Completo", "location": "Detrás de la apófisis mastoides.", "indications": ["insomnio", "rigidez cervical", "calmar el shen"] },
    "GB13": { "code": "GB13", "meridian": "GB", "chinese": "本神", "pinyin": "Běn Shén", "spanish": "Raíz del Espíritu", "location": "—", "indications": ["epilepsia", "calmar trastornos mentales"] },
    "GB14": { "code": "GB14", "meridian": "GB", "chinese": "陽白", "pinyin": "Yáng Bái", "spanish": "Yang Blanco", "location": "1 cun por encima de la mitad de la ceja.", "indications": ["cefalea frontal", "parálisis facial", "trastornos oculares"] },
    "GB15": { "code": "GB15", "meridian": "GB", "chinese": "頭臨泣", "pinyin": "Tóu Lín Qì", "spanish": "Lágrimas Sobre la Cabeza", "location": "—", "indications": [] },
    "GB16": { "code": "GB16", "meridian": "GB", "chinese": "目窗", "pinyin": "Mù Chuāng", "spanish": "Ventana del Ojo", "location": "—", "indications": [] },
    "GB17": { "code": "GB17", "meridian": "GB", "chinese": "正營", "pinyin": "Zhèng Yíng", "spanish": "Construcción Correcta", "location": "—", "indications": [] },
    "GB18": { "code": "GB18", "meridian": "GB", "chinese": "承靈", "pinyin": "Chéng Líng", "spanish": "Receptor del Espíritu", "location": "—", "indications": [] },
    "GB19": { "code": "GB19", "meridian": "GB", "chinese": "腦空", "pinyin": "Nǎo Kōng", "spanish": "Vacío del Cerebro", "location": "—", "indications": [] },
    "GB20": { "code": "GB20", "meridian": "GB", "chinese": "風池", "pinyin": "Fēng Chí", "spanish": "Estanque del Viento", "location": "Bajo el occipucio, en la depresión entre el ECM y el trapecio.", "indications": ["cefalea", "rigidez cervical", "vértigo", "resfriados", "hipertensión"] },
    "GB21": { "code": "GB21", "meridian": "GB", "chinese": "肩井", "pinyin": "Jiān Jǐng", "spanish": "Pozo del Hombro", "location": "Punto medio entre GV14 y el acromion, sobre el trapecio.", "indications": ["tensión de hombros", "cefalea cervical", "parto difícil (contraindicado en embarazo)"] },
    "GB22": { "code": "GB22", "meridian": "GB", "chinese": "淵腋", "pinyin": "Yuān Yè", "spanish": "Abismo Axilar", "location": "—", "indications": [] },
    "GB23": { "code": "GB23", "meridian": "GB", "chinese": "輒筋", "pinyin": "Zhé Jīn", "spanish": "Tendón Lateral", "location": "—", "indications": [] },
    "GB24": { "code": "GB24", "meridian": "GB", "chinese": "日月", "pinyin": "Rì Yuè", "spanish": "Sol y Luna", "category": ["mu de la Vesícula"], "location": "—", "indications": ["trastornos hepatobiliares"] },
    "GB25": { "code": "GB25", "meridian": "GB", "chinese": "京門", "pinyin": "Jīng Mén", "spanish": "Puerta de la Capital", "category": ["mu del Riñón"], "location": "—", "indications": [] },
    "GB26": { "code": "GB26", "meridian": "GB", "chinese": "帶脈", "pinyin": "Dài Mài", "spanish": "Vaso Cinturón", "location": "—", "indications": ["leucorrea", "trastornos del Dai Mai (cinturón)"] },
    "GB27": { "code": "GB27", "meridian": "GB", "chinese": "五樞", "pinyin": "Wǔ Shū", "spanish": "Cinco Ejes", "location": "—", "indications": [] },
    "GB28": { "code": "GB28", "meridian": "GB", "chinese": "維道", "pinyin": "Wéi Dào", "spanish": "Camino que Une", "location": "—", "indications": [] },
    "GB29": { "code": "GB29", "meridian": "GB", "chinese": "居髎", "pinyin": "Jū Liáo", "spanish": "Hueso de la Residencia", "location": "—", "indications": [] },
    "GB30": { "code": "GB30", "meridian": "GB", "chinese": "環跳", "pinyin": "Huán Tiào", "spanish": "Salto en Círculo", "location": "Entre el trocánter mayor y el sacro.", "indications": ["ciática (punto principal)", "dolor de cadera", "lumbalgia baja"] },
    "GB31": { "code": "GB31", "meridian": "GB", "chinese": "風市", "pinyin": "Fēng Shì", "spanish": "Mercado del Viento", "location": "Cara lateral del muslo, donde llega el dedo medio con el brazo extendido.", "indications": ["prurito generalizado", "dolor lateral del muslo"] },
    "GB32": { "code": "GB32", "meridian": "GB", "chinese": "中瀆", "pinyin": "Zhōng Dú", "spanish": "Río Central", "location": "—", "indications": [] },
    "GB33": { "code": "GB33", "meridian": "GB", "chinese": "膝陽關", "pinyin": "Xī Yáng Guān", "spanish": "Paso Yang de la Rodilla", "location": "—", "indications": [] },
    "GB34": { "code": "GB34", "meridian": "GB", "chinese": "陽陵泉", "pinyin": "Yáng Líng Quán", "spanish": "Fuente de la Colina Yang", "category": ["he-mar", "reunión de los tendones"], "location": "Bajo y anterior a la cabeza del peroné.", "indications": ["trastornos tendinosos", "dolor de rodilla externa", "ictericia", "hígado-vesícula"] },
    "GB35": { "code": "GB35", "meridian": "GB", "chinese": "陽交", "pinyin": "Yáng Jiāo", "spanish": "Cruce Yang", "category": ["xi del Yang Wei"], "location": "—", "indications": [] },
    "GB36": { "code": "GB36", "meridian": "GB", "chinese": "外丘", "pinyin": "Wài Qiū", "spanish": "Loma Externa", "category": ["xi-acumulación"], "location": "—", "indications": [] },
    "GB37": { "code": "GB37", "meridian": "GB", "chinese": "光明", "pinyin": "Guāng Míng", "spanish": "Resplandor Brillante", "category": ["luo"], "location": "—", "indications": ["trastornos oculares"] },
    "GB38": { "code": "GB38", "meridian": "GB", "chinese": "陽輔", "pinyin": "Yáng Fǔ", "spanish": "Asistente Yang", "category": ["jing-río"], "location": "—", "indications": [] },
    "GB39": { "code": "GB39", "meridian": "GB", "chinese": "懸鐘", "pinyin": "Xuán Zhōng", "spanish": "Campana Suspendida", "category": ["reunión de los Médulas"], "location": "3 cun por encima del maléolo externo, en el borde anterior del peroné.", "indications": ["rigidez cervical", "trastornos óseos y de médula"] },
    "GB40": { "code": "GB40", "meridian": "GB", "chinese": "丘墟", "pinyin": "Qiū Xū", "spanish": "Loma de la Ruina", "category": ["yuan"], "location": "—", "indications": [] },
    "GB41": { "code": "GB41", "meridian": "GB", "chinese": "足臨泣", "pinyin": "Zú Lín Qì", "spanish": "Lágrimas en el Pie", "category": ["shu-arroyo", "comando del Dai Mai"], "location": "Entre el 4º y 5º metatarsiano, en la unión de los huesos.", "indications": ["trastornos del Dai Mai", "cefalea temporal", "menstruación irregular"] },
    "GB42": { "code": "GB42", "meridian": "GB", "chinese": "地五會", "pinyin": "Dì Wǔ Huì", "spanish": "Cinco Reuniones de la Tierra", "location": "—", "indications": [] },
    "GB43": { "code": "GB43", "meridian": "GB", "chinese": "俠谿", "pinyin": "Xiá Xī", "spanish": "Arroyo Insertado", "category": ["ying-manantial"], "location": "—", "indications": [] },
    "GB44": { "code": "GB44", "meridian": "GB", "chinese": "足竅陰", "pinyin": "Zú Qiào Yīn", "spanish": "Yin de los Orificios del Pie", "category": ["jing-pozo"], "location": "—", "indications": [] },

    "LV1": { "code": "LV1", "meridian": "LV", "chinese": "大敦", "pinyin": "Dà Dūn", "spanish": "Gran Sólido", "category": ["jing-pozo"], "location": "Esquina ungueal lateral del primer dedo del pie.", "indications": ["dismenorrea", "hernia inguinal", "trastornos genitales"] },
    "LV2": { "code": "LV2", "meridian": "LV", "chinese": "行間", "pinyin": "Xíng Jiān", "spanish": "Espacio Móvil", "category": ["ying-manantial"], "location": "Entre el 1er y 2º dedo del pie, en la unión piel roja/blanca.", "indications": ["calor en el Hígado", "irritabilidad", "ojos rojos"] },
    "LV3": { "code": "LV3", "meridian": "LV", "chinese": "太衝", "pinyin": "Tài Chōng", "spanish": "Asalto Supremo", "category": ["yuan", "shu-arroyo"], "location": "Entre el 1er y 2º metatarsiano, en la depresión proximal de la unión de los huesos.", "indications": ["estancamiento de qi de Hígado", "irritabilidad", "cefalea por tensión", "trastornos menstruales", "ojos"] },
    "LV4": { "code": "LV4", "meridian": "LV", "chinese": "中封", "pinyin": "Zhōng Fēng", "spanish": "Sello Central", "category": ["jing-río"], "location": "—", "indications": [] },
    "LV5": { "code": "LV5", "meridian": "LV", "chinese": "蠡溝", "pinyin": "Lí Gōu", "spanish": "Surco del Insecto", "category": ["luo"], "location": "—", "indications": ["genitales", "leucorrea"] },
    "LV6": { "code": "LV6", "meridian": "LV", "chinese": "中都", "pinyin": "Zhōng Dū", "spanish": "Capital Central", "category": ["xi-acumulación"], "location": "—", "indications": [] },
    "LV7": { "code": "LV7", "meridian": "LV", "chinese": "膝關", "pinyin": "Xī Guān", "spanish": "Paso de la Rodilla", "location": "—", "indications": [] },
    "LV8": { "code": "LV8", "meridian": "LV", "chinese": "曲泉", "pinyin": "Qū Quán", "spanish": "Manantial Curvo", "category": ["he-mar"], "location": "—", "indications": ["dolor de rodilla interno", "humedad genital"] },
    "LV9": { "code": "LV9", "meridian": "LV", "chinese": "陰包", "pinyin": "Yīn Bāo", "spanish": "Envoltura Yin", "location": "—", "indications": [] },
    "LV10": { "code": "LV10", "meridian": "LV", "chinese": "足五里", "pinyin": "Zú Wǔ Lǐ", "spanish": "Cinco Distancias del Pie", "location": "—", "indications": [] },
    "LV11": { "code": "LV11", "meridian": "LV", "chinese": "陰廉", "pinyin": "Yīn Lián", "spanish": "Borde Yin", "location": "—", "indications": [] },
    "LV12": { "code": "LV12", "meridian": "LV", "chinese": "急脈", "pinyin": "Jí Mài", "spanish": "Vaso Urgente", "location": "—", "indications": [] },
    "LV13": { "code": "LV13", "meridian": "LV", "chinese": "章門", "pinyin": "Zhāng Mén", "spanish": "Puerta del Capítulo", "category": ["mu del Bazo", "reunión de los Zang"], "location": "Borde libre de la 11ª costilla.", "indications": ["digestión débil", "distensión abdominal", "trastornos de los órganos yin"] },
    "LV14": { "code": "LV14", "meridian": "LV", "chinese": "期門", "pinyin": "Qī Mén", "spanish": "Puerta del Ciclo", "category": ["mu del Hígado"], "location": "6º espacio intercostal, en la línea del pezón.", "indications": ["dolor costal", "trastornos hepáticos", "frustración estancada"] },

    "GV1": { "code": "GV1", "meridian": "GV", "chinese": "長強", "pinyin": "Cháng Qiáng", "spanish": "Larga Fuerza", "category": ["luo del Du Mai"], "location": "Entre la punta del cóccix y el ano.", "indications": ["hemorroides", "prolapso rectal"] },
    "GV2": { "code": "GV2", "meridian": "GV", "chinese": "腰俞", "pinyin": "Yāo Shū", "spanish": "Shu de la Cintura", "location": "—", "indications": [] },
    "GV3": { "code": "GV3", "meridian": "GV", "chinese": "腰陽關", "pinyin": "Yāo Yáng Guān", "spanish": "Paso Yang Lumbar", "location": "—", "indications": [] },
    "GV4": { "code": "GV4", "meridian": "GV", "chinese": "命門", "pinyin": "Mìng Mén", "spanish": "Puerta de la Vida", "location": "Entre L2 y L3, en la línea media.", "indications": ["deficiencia de Yang Riñón", "lumbalgia crónica fría", "vitalidad general"] },
    "GV5": { "code": "GV5", "meridian": "GV", "chinese": "懸樞", "pinyin": "Xuán Shū", "spanish": "Eje Suspendido", "location": "—", "indications": [] },
    "GV6": { "code": "GV6", "meridian": "GV", "chinese": "脊中", "pinyin": "Jǐ Zhōng", "spanish": "Centro de la Columna", "location": "—", "indications": [] },
    "GV7": { "code": "GV7", "meridian": "GV", "chinese": "中樞", "pinyin": "Zhōng Shū", "spanish": "Eje Central", "location": "—", "indications": [] },
    "GV8": { "code": "GV8", "meridian": "GV", "chinese": "筋縮", "pinyin": "Jīn Suō", "spanish": "Contractura de Tendones", "location": "—", "indications": [] },
    "GV9": { "code": "GV9", "meridian": "GV", "chinese": "至陽", "pinyin": "Zhì Yáng", "spanish": "Llegada al Yang", "location": "—", "indications": [] },
    "GV10": { "code": "GV10", "meridian": "GV", "chinese": "靈台", "pinyin": "Líng Tái", "spanish": "Plataforma del Espíritu", "location": "—", "indications": [] },
    "GV11": { "code": "GV11", "meridian": "GV", "chinese": "神道", "pinyin": "Shén Dào", "spanish": "Camino del Espíritu", "location": "—", "indications": [] },
    "GV12": { "code": "GV12", "meridian": "GV", "chinese": "身柱", "pinyin": "Shēn Zhù", "spanish": "Pilar del Cuerpo", "location": "—", "indications": [] },
    "GV13": { "code": "GV13", "meridian": "GV", "chinese": "陶道", "pinyin": "Táo Dào", "spanish": "Camino del Alfarero", "location": "—", "indications": [] },
    "GV14": { "code": "GV14", "meridian": "GV", "chinese": "大椎", "pinyin": "Dà Zhuī", "spanish": "Gran Vértebra", "location": "Bajo la apófisis espinosa de C7.", "indications": ["fiebres", "dispersar calor", "rigidez cervical-dorsal", "fortalecer el yang"] },
    "GV15": { "code": "GV15", "meridian": "GV", "chinese": "啞門", "pinyin": "Yǎ Mén", "spanish": "Puerta de la Mudez", "location": "—", "indications": [] },
    "GV16": { "code": "GV16", "meridian": "GV", "chinese": "風府", "pinyin": "Fēng Fǔ", "spanish": "Palacio del Viento", "location": "—", "indications": [] },
    "GV17": { "code": "GV17", "meridian": "GV", "chinese": "腦戶", "pinyin": "Nǎo Hù", "spanish": "Puerta del Cerebro", "location": "—", "indications": [] },
    "GV18": { "code": "GV18", "meridian": "GV", "chinese": "強間", "pinyin": "Qiáng Jiān", "spanish": "Espacio Firme", "location": "—", "indications": [] },
    "GV19": { "code": "GV19", "meridian": "GV", "chinese": "後頂", "pinyin": "Hòu Dǐng", "spanish": "Vértice Posterior", "location": "—", "indications": [] },
    "GV20": { "code": "GV20", "meridian": "GV", "chinese": "百會", "pinyin": "Bǎi Huì", "spanish": "Reunión de los Cien", "location": "Vértex craneal, en el cruce de la línea media con la línea entre los ápices de las orejas.", "indications": ["claridad mental", "elevar el yang", "prolapsos", "cefalea por exceso", "depresión"] },
    "GV21": { "code": "GV21", "meridian": "GV", "chinese": "前頂", "pinyin": "Qián Dǐng", "spanish": "Vértice Anterior", "location": "—", "indications": [] },
    "GV22": { "code": "GV22", "meridian": "GV", "chinese": "顖會", "pinyin": "Xìn Huì", "spanish": "Reunión de la Fontanela", "location": "—", "indications": [] },
    "GV23": { "code": "GV23", "meridian": "GV", "chinese": "上星", "pinyin": "Shàng Xīng", "spanish": "Estrella Superior", "location": "—", "indications": [] },
    "GV24": { "code": "GV24", "meridian": "GV", "chinese": "神庭", "pinyin": "Shén Tíng", "spanish": "Patio del Espíritu", "location": "—", "indications": [] },
    "GV25": { "code": "GV25", "meridian": "GV", "chinese": "素髎", "pinyin": "Sù Liáo", "spanish": "Hueso Pálido", "location": "—", "indications": [] },
    "GV26": { "code": "GV26", "meridian": "GV", "chinese": "水溝", "pinyin": "Shuǐ Gōu", "spanish": "Surco del Agua", "location": "Tercio superior del filtro nasal.", "indications": ["pérdida de consciencia", "shock", "dolor lumbar agudo (clásico)"] },
    "GV27": { "code": "GV27", "meridian": "GV", "chinese": "兌端", "pinyin": "Duì Duān", "spanish": "Extremo del Intercambio", "location": "—", "indications": [] },
    "GV28": { "code": "GV28", "meridian": "GV", "chinese": "齦交", "pinyin": "Yín Jiāo", "spanish": "Cruce de las Encías", "location": "—", "indications": [] },

    "CV1": { "code": "CV1", "meridian": "CV", "chinese": "會陰", "pinyin": "Huì Yīn", "spanish": "Reunión del Yin", "location": "Punto medio del periné.", "indications": ["pérdida de consciencia (con yin frío)", "trastornos perineales"] },
    "CV2": { "code": "CV2", "meridian": "CV", "chinese": "曲骨", "pinyin": "Qū Gǔ", "spanish": "Hueso Curvo", "location": "—", "indications": [] },
    "CV3": { "code": "CV3", "meridian": "CV", "chinese": "中極", "pinyin": "Zhōng Jí", "spanish": "Centro Extremo", "category": ["mu de la Vejiga"], "location": "—", "indications": ["trastornos urogenitales"] },
    "CV4": { "code": "CV4", "meridian": "CV", "chinese": "關元", "pinyin": "Guān Yuán", "spanish": "Origen de la Barrera", "category": ["mu del Intestino Delgado"], "location": "3 cun por debajo del ombligo, en la línea media.", "indications": ["tonificar yuan qi", "fatiga crónica", "deficiencia de Riñón", "trastornos ginecológicos"] },
    "CV5": { "code": "CV5", "meridian": "CV", "chinese": "石門", "pinyin": "Shí Mén", "spanish": "Puerta de Piedra", "category": ["mu del Triple Calentador"], "location": "—", "indications": [] },
    "CV6": { "code": "CV6", "meridian": "CV", "chinese": "氣海", "pinyin": "Qì Hǎi", "spanish": "Mar de Qi", "location": "1.5 cun por debajo del ombligo, en la línea media.", "indications": ["fatiga", "deficiencia de qi", "tonificar yang general"] },
    "CV7": { "code": "CV7", "meridian": "CV", "chinese": "陰交", "pinyin": "Yīn Jiāo", "spanish": "Cruce del Yin", "location": "—", "indications": [] },
    "CV8": { "code": "CV8", "meridian": "CV", "chinese": "神闕", "pinyin": "Shén Què", "spanish": "Palacio del Espíritu (Ombligo)", "location": "Centro del ombligo. No se puntura — solo moxa.", "indications": ["tonificación profunda con moxa", "diarrea crónica", "shock con yin frío"] },
    "CV9": { "code": "CV9", "meridian": "CV", "chinese": "水分", "pinyin": "Shuǐ Fēn", "spanish": "División del Agua", "location": "—", "indications": ["edema"] },
    "CV10": { "code": "CV10", "meridian": "CV", "chinese": "下脘", "pinyin": "Xià Wǎn", "spanish": "Abdomen Inferior", "location": "—", "indications": [] },
    "CV11": { "code": "CV11", "meridian": "CV", "chinese": "建里", "pinyin": "Jiàn Lǐ", "spanish": "Construir el Interior", "location": "—", "indications": [] },
    "CV12": { "code": "CV12", "meridian": "CV", "chinese": "中脘", "pinyin": "Zhōng Wǎn", "spanish": "Abdomen Central", "category": ["mu del Estómago", "reunión de los Fu"], "location": "4 cun por encima del ombligo, en la línea media.", "indications": ["trastornos digestivos", "dolor de estómago", "vómitos", "punto principal del Fu"] },
    "CV13": { "code": "CV13", "meridian": "CV", "chinese": "上脘", "pinyin": "Shàng Wǎn", "spanish": "Abdomen Superior", "location": "—", "indications": [] },
    "CV14": { "code": "CV14", "meridian": "CV", "chinese": "巨闕", "pinyin": "Jù Què", "spanish": "Gran Palacio", "category": ["mu del Corazón"], "location": "—", "indications": [] },
    "CV15": { "code": "CV15", "meridian": "CV", "chinese": "鳩尾", "pinyin": "Jiū Wěi", "spanish": "Cola de la Paloma", "category": ["luo del Ren Mai"], "location": "—", "indications": [] },
    "CV16": { "code": "CV16", "meridian": "CV", "chinese": "中庭", "pinyin": "Zhōng Tíng", "spanish": "Patio Central", "location": "—", "indications": [] },
    "CV17": { "code": "CV17", "meridian": "CV", "chinese": "膻中", "pinyin": "Dàn Zhōng", "spanish": "Centro del Pecho", "category": ["mu del Pericardio", "reunión del Qi"], "location": "Línea media del esternón, a la altura del 4º espacio intercostal (entre los pezones en hombres).", "indications": ["opresión torácica", "ansiedad", "insuficiencia de qi pulmonar/cardiaco"] },
    "CV18": { "code": "CV18", "meridian": "CV", "chinese": "玉堂", "pinyin": "Yù Táng", "spanish": "Salón de Jade", "location": "—", "indications": [] },
    "CV19": { "code": "CV19", "meridian": "CV", "chinese": "紫宮", "pinyin": "Zǐ Gōng", "spanish": "Palacio Púrpura", "location": "—", "indications": [] },
    "CV20": { "code": "CV20", "meridian": "CV", "chinese": "華蓋", "pinyin": "Huá Gài", "spanish": "Dosel Florecido", "location": "—", "indications": [] },
    "CV21": { "code": "CV21", "meridian": "CV", "chinese": "璇璣", "pinyin": "Xuán Jī", "spanish": "Telar Estelar", "location": "—", "indications": [] },
    "CV22": { "code": "CV22", "meridian": "CV", "chinese": "天突", "pinyin": "Tiān Tū", "spanish": "Saliente Celestial", "location": "Hueco supraesternal.", "indications": ["tos", "asma", "afonía", "garganta"] },
    "CV23": { "code": "CV23", "meridian": "CV", "chinese": "廉泉", "pinyin": "Lián Quán", "spanish": "Manantial del Borde", "location": "—", "indications": ["afasia", "trastornos de la lengua"] },
    "CV24": { "code": "CV24", "meridian": "CV", "chinese": "承漿", "pinyin": "Chéng Jiāng", "spanish": "Receptor de los Líquidos", "location": "Centro del surco mentolabial.", "indications": ["parálisis facial", "babeo"] }
  }
}
